{"totalZones":3,"geoJson":{"type":"FeatureCollection","features":[{"type":"Feature","properties":{"zoneId":"zone-1","name":"FLOOD-LANDSLIDE Zone 1","typologyLabel":"FLOOD_LANDSLIDE","primaryHazard":"flood","interventionType":"sponge_network","meanFlood":0.45,"meanHeat":0.27,"meanLandslide":0.37,"areaKm2":647,"cellCount":647},"geometry":{"type":"Polygon","coordinates":[[[-51.3034404,-30.2694499],[-51.01598082400278,-30.2694499],[-51.01598082400278,-29.92809165350344],[-51.3034404,-29.92809165350344],[-51.3034404,-30.2694499]]]}},{"type":"Feature","properties":{"zoneId":"zone-2","name":"FLOOD-HEAT Zone 2","typologyLabel":"FLOOD_HEAT","primaryHazard":"flood","interventionType":"multi_benefit","meanFlood":0.62,"meanHeat":0.45,"meanLandslide":0.33,"areaKm2":446,"cellCount":446},"geometry":{"type":"Polygon","coordinates":[[[-51.294457288250086,-30.260466788250092],[-51.01598082400278,-30.260466788250092],[-51.01598082400278,-29.92809165350344],[-51.294457288250086,-29.92809165350344],[-51.294457288250086,-30.260466788250092]]]}},{"type":"Feature","properties":{"zoneId":"zone-3","name":"FLOOD Zone 3","typologyLabel":"FLOOD","primaryHazard":"flood","interventionType":"sponge_network","meanFlood":0.52,"meanHeat":0.17,"meanLandslide":0.29,"areaKm2":20,"cellCount":20},"geometry":{"type":"Polygon","coordinates":[[[-51.258524841250434,-30.197585006000725],[-51.06987949450226,-30.197585006000725],[-51.06987949450226,-30.12572011200145],[-51.258524841250434,-30.12572011200145],[-51.258524841250434,-30.197585006000725]]]}}]}}